p2p/__about__.py
p2p/__init__.py
p2p/cli.py
p2p_py-0.0.1.dist-info/METADATA
p2p_py-0.0.1.dist-info/WHEEL
p2p_py-0.0.1.dist-info/licenses/LICENSE.txt
p2p_py-0.0.1.dist-info/RECORD
