Metadata-Version: 2.1
Name: p2p_py
Version: 0.0.1
Project-URL: Documentation, https://github.com/unknown/p2p#readme
Project-URL: Issues, https://github.com/unknown/p2p/issues
Project-URL: Source, https://github.com/unknown/p2p
Author-email: Ashween Mankash <ashweenmankash@gmail.com>
License-Expression: MIT
License-File: LICENSE.txt
Classifier: Development Status :: 4 - Beta
Classifier: Programming Language :: Python
Classifier: Programming Language :: Python :: 3.8
Classifier: Programming Language :: Python :: 3.9
Classifier: Programming Language :: Python :: 3.10
Classifier: Programming Language :: Python :: 3.11
Classifier: Programming Language :: Python :: 3.12
Classifier: Programming Language :: Python :: Implementation :: CPython
Classifier: Programming Language :: Python :: Implementation :: PyPy
Requires-Python: >=3.8
Requires-Dist: typer
